adafruit_circuitpython_pcf8523-2.0.7.dist-info/licenses/LICENSE
adafruit_pcf8523/clock.py
adafruit_pcf8523/pcf8523.py
adafruit_pcf8523/timer.py
adafruit_circuitpython_pcf8523-2.0.7.dist-info/METADATA
adafruit_circuitpython_pcf8523-2.0.7.dist-info/WHEEL
adafruit_circuitpython_pcf8523-2.0.7.dist-info/top_level.txt
adafruit_circuitpython_pcf8523-2.0.7.dist-info/RECORD
